{
  "type": "Feature",
  "properties": {
    "iso:country":"IE",
    "sg:address":"14 cherryorchard park ballyfermot",
    "sg:city":"dublin",
    "sg:classifiers":[
        {
            "category":"Professional",
            "subcategory":"Computer Services",
            "type":"Services"
        }
    ],
    "sg:postcode":"d10",
    "sg:tags":[
        "music",
        "review",
        "cd",
        "album",
        "live"
    ],
    "sg:website":"http://www.musicreveiw.com",
    "wof:name":"Musicreview",
    "wof:placetype":"venue"
},
  "geometry": {"coordinates":[-6.371726,53.335773],"type":"Point"}
}