{
  "type": "Feature",
  "properties": {
    "iso:country":"IE",
    "sg:address":"Courtyard Offices 44 Westland Row",
    "sg:city":"Dublin",
    "sg:classifiers":[
        {
            "category":"Professional",
            "subcategory":"Computer Services",
            "type":"Services"
        }
    ],
    "sg:postcode":"D2",
    "sg:tags":[
        "web2ireland",
        "health",
        "dental-tourism",
        "medical-tourism",
        "search-engine",
        "dentists",
        "dental",
        "clinics",
        "directory",
        "cosmetic-surgery"
    ],
    "sg:website":"http://www.whatclinic.com",
    "wof:name":"WhatClinic.com",
    "wof:placetype":"venue"
},
  "geometry": {"coordinates":[-6.249879,53.343103],"type":"Point"}
}