{
  "type": "Feature",
  "properties": {
    "iso:country":"IE",
    "sg:address":"8 Clanwilliam Terrace,",
    "sg:city":"Dublin",
    "sg:classifiers":[
        {
            "category":"Professional",
            "subcategory":"Business Services",
            "type":"Services"
        }
    ],
    "sg:postcode":"D2",
    "sg:tags":[
        "voip",
        "phone",
        "telephony",
        "ireland",
        "tech"
    ],
    "sg:website":"http://www.blueface.ie",
    "wof:name":"Blueface",
    "wof:placetype":"venue"
},
  "geometry": {"coordinates":[-6.239955,53.338093],"type":"Point"}
}