{
  "type": "Feature",
  "properties": {
    "iso:country":"IE",
    "sg:address":"4 St Catherines Lane West The Digital Hub",
    "sg:city":"Dublin",
    "sg:classifiers":[
        {
            "category":"Professional",
            "subcategory":"Computer Services",
            "type":"Services"
        }
    ],
    "sg:postcode":"8",
    "sg:tags":[
        "mobile-apps",
        "mobile"
    ],
    "sg:website":"http://www.mobileaware.com",
    "wof:name":"MobileAware",
    "wof:placetype":"venue"
},
  "geometry": {"coordinates":[-6.280957,53.342648],"type":"Point"}
}