{
  "type": "Feature",
  "properties": {
    "iso:country":"IE",
    "sg:address":"1 Rock Road",
    "sg:city":"Blackrock",
    "sg:classifiers":[
        {
            "category":"Professional",
            "subcategory":"Computer Services",
            "type":"Services"
        }
    ],
    "sg:postcode":"Co. Dublin",
    "sg:tags":[
        "mobile-location-social",
        "web2ireland"
    ],
    "sg:website":"http://www.locle.com",
    "wof:name":"Locle",
    "wof:placetype":"venue"
},
  "geometry": {"coordinates":[-6.1947866,53.3080323],"type":"Point"}
}