{
  "type": "Feature",
  "properties": {
    "iso:country":"IE",
    "sg:address":"Tyrconnell Park, Inchicore",
    "sg:city":"Dublin",
    "sg:classifiers":[
        {
            "category":"Professional",
            "subcategory":"Computer Services",
            "type":"Services"
        }
    ],
    "sg:postcode":"00008",
    "sg:tags":[
        "accounting",
        "finance",
        "bookkeeping",
        "small-business",
        "extranet",
        "accounts"
    ],
    "sg:website":"http://www.yendo.com",
    "wof:name":"Yendo",
    "wof:placetype":"venue"
},
  "geometry": {"coordinates":[-6.32868,53.337935],"type":"Point"}
}