{
  "type": "Feature",
  "properties": {
    "iso:country":"IE",
    "sg:address":"2 Castle Terrace Malahide",
    "sg:city":"Dublin",
    "sg:classifiers":[
        {
            "category":"Professional",
            "subcategory":"Business Services",
            "type":"Services"
        }
    ],
    "sg:postcode":"EIRE",
    "sg:tags":[
        "web2ireland",
        "time-tracking",
        "timesheets",
        "project",
        "employee",
        "project-management",
        "software"
    ],
    "sg:website":"http://1timetracking.com",
    "wof:name":"Time Warden",
    "wof:placetype":"venue"
},
  "geometry": {"coordinates":[-6.1071512,53.2781561],"type":"Point"}
}